format_cef/__init__.py
format_cef/cef.py
format_cef/legacy.py
format_cef/_cef/__init__.py
format_cef/_cef/base.py
format_cef/_cef/compat.py
format_cef/_cef/legacy_extensions.csv
format_cef/_cef/valid_extensions.csv
format_cef-0.0.4.dist-info/LICENSE
format_cef-0.0.4.dist-info/METADATA
format_cef-0.0.4.dist-info/WHEEL
format_cef-0.0.4.dist-info/top_level.txt
format_cef-0.0.4.dist-info/zip-safe
format_cef-0.0.4.dist-info/RECORD
