Metadata-Version: 2.1
Name: format-cef
Version: 0.0.4
Summary: A small helper for formatting ArcSight Common Event Format (CEF) compliant messages
Home-page: https://github.com/Osirium/format_cef
License: UNKNOWN
Keywords: cef,logging
Platform: UNKNOWN
Requires-Dist: six (~=1.12)
Requires-Dist: importlib-resources (~=1.0) ; python_version < "3.7"
